rangen/__init__.py
rangen/__main__.py
rangen/rangen.py
rangen-0.1.dist-info/LICENCE
rangen-0.1.dist-info/METADATA
rangen-0.1.dist-info/WHEEL
rangen-0.1.dist-info/entry_points.txt
rangen-0.1.dist-info/top_level.txt
rangen-0.1.dist-info/RECORD
