Metadata-Version: 2.1
Name: rangen
Version: 0.1
Summary: Rangen is a random string generator.
Home-page: https://github.com/Vinz2008/rangen
Author: Vincent Bidard de la Noë
Author-email: vincentbidarddelanoe@gmail.com
License: UNKNOWN
Platform: UNKNOWN
Classifier: Programming Language :: Python :: 3
Classifier: License :: OSI Approved :: MIT License
Classifier: Operating System :: OS Independent
License-File: LICENCE
